roto/__init__.py
roto/_grad.py
roto/_roto.py
roto-1.1.0.dist-info/LICENSE
roto-1.1.0.dist-info/METADATA
roto-1.1.0.dist-info/WHEEL
roto-1.1.0.dist-info/top_level.txt
roto-1.1.0.dist-info/RECORD
