Metadata-Version: 2.1
Name: roto
Version: 1.1.0
Summary: UNKNOWN
Home-page: https://github.com/we-taper/roto.git
Author: Hongxiang Chen
Author-email: h.chen.17@ucl.ac.uk
License: UNKNOWN
Platform: UNKNOWN
Classifier: Development Status :: 4 - Beta
Classifier: Intended Audience :: Science/Research
Classifier: Topic :: Software Development :: Build Tools
Classifier: License :: OSI Approved :: GNU General Public License v3 (GPLv3)
Classifier: Programming Language :: Python :: 3 :: Only
Requires-Python: >=3.6, <4
Requires-Dist: numpy
Requires-Dist: scipy
